vertysimplemoduleaupmanyu/__init__.py
vertysimplemoduleaupmanyu/add.py
vertysimplemoduleaupmanyu/subtract.py
vertysimplemoduleaupmanyu/extras/__init__.py
vertysimplemoduleaupmanyu/extras/divide.py
vertysimplemoduleaupmanyu/extras/multiply.py
verysimplemoduleaupmanyu-0.0.1.dist-info/METADATA
verysimplemoduleaupmanyu-0.0.1.dist-info/WHEEL
verysimplemoduleaupmanyu-0.0.1.dist-info/top_level.txt
verysimplemoduleaupmanyu-0.0.1.dist-info/RECORD
